cdktf_cdktf_provider_azurerm/__init__.py
cdktf_cdktf_provider_azurerm/py.typed
cdktf_cdktf_provider_azurerm/_jsii/__init__.py
cdktf_cdktf_provider_azurerm/_jsii/provider-azurerm@14.21.0.jsii.tgz
cdktf_cdktf_provider_azurerm/aadb2_c_directory/__init__.py
cdktf_cdktf_provider_azurerm/active_directory_domain_service/__init__.py
cdktf_cdktf_provider_azurerm/active_directory_domain_service_replica_set/__init__.py
cdktf_cdktf_provider_azurerm/active_directory_domain_service_trust/__init__.py
cdktf_cdktf_provider_azurerm/advanced_threat_protection/__init__.py
cdktf_cdktf_provider_azurerm/advisor_suppression/__init__.py
cdktf_cdktf_provider_azurerm/ai_foundry/__init__.py
cdktf_cdktf_provider_azurerm/ai_foundry_project/__init__.py
cdktf_cdktf_provider_azurerm/ai_services/__init__.py
cdktf_cdktf_provider_azurerm/analysis_services_server/__init__.py
cdktf_cdktf_provider_azurerm/api_connection/__init__.py
cdktf_cdktf_provider_azurerm/api_management/__init__.py
cdktf_cdktf_provider_azurerm/api_management_api/__init__.py
cdktf_cdktf_provider_azurerm/api_management_api_diagnostic/__init__.py
cdktf_cdktf_provider_azurerm/api_management_api_operation/__init__.py
cdktf_cdktf_provider_azurerm/api_management_api_operation_policy/__init__.py
cdktf_cdktf_provider_azurerm/api_management_api_operation_tag/__init__.py
cdktf_cdktf_provider_azurerm/api_management_api_policy/__init__.py
cdktf_cdktf_provider_azurerm/api_management_api_release/__init__.py
cdktf_cdktf_provider_azurerm/api_management_api_schema/__init__.py
cdktf_cdktf_provider_azurerm/api_management_api_tag/__init__.py
cdktf_cdktf_provider_azurerm/api_management_api_tag_description/__init__.py
cdktf_cdktf_provider_azurerm/api_management_api_version_set/__init__.py
cdktf_cdktf_provider_azurerm/api_management_authorization_server/__init__.py
cdktf_cdktf_provider_azurerm/api_management_backend/__init__.py
cdktf_cdktf_provider_azurerm/api_management_certificate/__init__.py
cdktf_cdktf_provider_azurerm-14.21.0.dist-info/LICENSE
cdktf_cdktf_provider_azurerm-14.21.0.dist-info/METADATA
cdktf_cdktf_provider_azurerm-14.21.0.dist-info/WHEEL
cdktf_cdktf_provider_azurerm-14.21.0.dist-info/top_level.txt
cdktf_cdktf_provider_azurerm-14.21.0.dist-info/RECORD
